normscaler/__init__.py
normscaler/scaler.py
normscaler-0.0.2.dist-info/LICENCE.txt
normscaler-0.0.2.dist-info/METADATA
normscaler-0.0.2.dist-info/WHEEL
normscaler-0.0.2.dist-info/top_level.txt
normscaler-0.0.2.dist-info/RECORD
