Metadata-Version: 2.1
Name: normscaler
Version: 0.0.2
Summary: A data normalization package
Home-page: https://github.com/shoukewei/normscaler
Author: Shouke Wei
Author-email: shouke.wei@gmail.com
License: MIT License
Keywords: python,data normalization,dataframe,one-hot encoded variables,train,test
Classifier: Development Status :: 1 - Planning
Classifier: Intended Audience :: Science/Research
Classifier: Programming Language :: Python :: 3
Classifier: Operating System :: Unix
Classifier: Operating System :: MacOS :: MacOS X
Classifier: Operating System :: Microsoft :: Windows
License-File: LICENCE.txt
Requires-Dist: pandas
Requires-Dist: scikit-learn
